pytest_phmdoctest/__init__.py
pytest_phmdoctest/collectors.py
pytest_phmdoctest/docmod.py
pytest_phmdoctest/plugin.py
pytest_phmdoctest/settings.py
pytest_phmdoctest-1.0.0.dist-info/LICENSE.txt
pytest_phmdoctest-1.0.0.dist-info/METADATA
pytest_phmdoctest-1.0.0.dist-info/WHEEL
pytest_phmdoctest-1.0.0.dist-info/entry_points.txt
pytest_phmdoctest-1.0.0.dist-info/top_level.txt
pytest_phmdoctest-1.0.0.dist-info/RECORD
