Metadata-Version: 2.1
Name: pytest-phmdoctest
Version: 1.0.0
Summary: pytest plugin to test Python examples in Markdown using phmdoctest.
Home-page: https://tmarktaylor.github.io/pytest-phmdoctest
Author: Mark Taylor
Author-email: mark66547ta2@gmail.com
License: MIT
Project-URL: Bug Reports, https://github.com/tmarktaylor/pytest-phmdoctest/issues
Project-URL: Source, https://github.com/tmarktaylor/pytest-phmdoctest/
Keywords: documentation,doctest,markdown,testing
Platform: UNKNOWN
Classifier: Development Status :: 4 - Beta
Classifier: Framework :: Pytest
Classifier: Intended Audience :: Developers
Classifier: Topic :: Software Development :: Testing
Classifier: Topic :: Software Development :: Documentation
Classifier: License :: OSI Approved :: MIT License
Classifier: Programming Language :: Python
Classifier: Programming Language :: Python :: 3
Classifier: Programming Language :: Python :: 3.7
Classifier: Programming Language :: Python :: 3.8
Classifier: Programming Language :: Python :: 3.9
Classifier: Programming Language :: Python :: 3.10
Classifier: Programming Language :: Python :: Implementation :: PyPy
Classifier: Operating System :: OS Independent
Requires-Python: >=3.6
License-File: LICENSE.txt
Requires-Dist: packaging
Requires-Dist: py
Requires-Dist: pytest (>=5.4.3)
Requires-Dist: phmdoctest (>=1.4.0)
Requires-Dist: commonmark (>=0.9.1)
Provides-Extra: docs
Requires-Dist: myst-parser (>=0.15.1) ; extra == 'docs'
Requires-Dist: sphinx (>=4.1.0) ; extra == 'docs'
Requires-Dist: sphinx-rtd-theme (>=1.0.0) ; extra == 'docs'
Requires-Dist: docutils (<0.17) ; extra == 'docs'
Provides-Extra: inspect
Requires-Dist: black ; extra == 'inspect'
Requires-Dist: flake8 ; extra == 'inspect'
Requires-Dist: pep8-naming ; extra == 'inspect'
Requires-Dist: check-manifest ; extra == 'inspect'
Requires-Dist: build ; extra == 'inspect'
Requires-Dist: twine ; extra == 'inspect'
Provides-Extra: test
Requires-Dist: coverage ; extra == 'test'
Requires-Dist: pytest (>=6.2) ; extra == 'test'
Requires-Dist: PyYAML (>=5.4.1) ; extra == 'test'
